Metadata-Version: 2.4
Name: fastapi-autodoc
Version: 1.0.11
Summary: A FastAPI library for generating and managing project documentation
Home-page: https://github.com/BisiOlaYemi/fastapi-auto-doc
Author: Yemi Ogunrinde
Author-email: ogunrinde_olayemi@yahoo.com
Classifier: Programming Language :: Python :: 3
Classifier: Framework :: FastAPI
Classifier: License :: OSI Approved :: MIT License
Classifier: Operating System :: OS Independent
Requires-Python: >=3.7
Requires-Dist: fastapi
Requires-Dist: uvicorn
Requires-Dist: click
Requires-Dist: pydantic
Requires-Dist: jinja2
Requires-Dist: python-dotenv
Requires-Dist: pydantic-settings
Requires-Dist: watchdog
Requires-Dist: typing-extensions
Requires-Dist: httpx
Requires-Dist: ast-comments
Requires-Dist: astroid
Requires-Dist: pathlib
Provides-Extra: dev
Requires-Dist: pytest; extra == "dev"
Requires-Dist: pytest-cov; extra == "dev"
Dynamic: author
Dynamic: author-email
Dynamic: classifier
Dynamic: description
Dynamic: description-content-type
Dynamic: home-page
Dynamic: provides-extra
Dynamic: requires-dist
Dynamic: requires-python
Dynamic: summary
